ttrsscli/__init__.py
ttrsscli/cache.py
ttrsscli/client.py
ttrsscli/config.py
ttrsscli/main.py
ttrsscli/py.typed
ttrsscli/ui/__init__.py
ttrsscli/ui/app.py
ttrsscli/ui/styles.tcss
ttrsscli/ui/widgets.py
ttrsscli/ui/screens/__init__.py
ttrsscli/ui/screens/confirm_screens.py
ttrsscli/ui/screens/feed_screens.py
ttrsscli/ui/screens/fullscreen.py
ttrsscli/ui/screens/help.py
ttrsscli/ui/screens/link_screens.py
ttrsscli/ui/screens/progress.py
ttrsscli/ui/screens/search.py
ttrsscli/utils/__init__.py
ttrsscli/utils/decorators.py
ttrsscli/utils/error_handling.py
ttrsscli/utils/markdown_converter.py
ttrsscli/utils/url.py
ttrsscli-0.3.1.dist-info/METADATA
ttrsscli-0.3.1.dist-info/WHEEL
ttrsscli-0.3.1.dist-info/entry_points.txt
ttrsscli-0.3.1.dist-info/licenses/LICENSE
ttrsscli-0.3.1.dist-info/RECORD
