Metadata-Version: 2.4
Name: ttrsscli
Version: 0.3.1
Summary: Textual tool to access a Tiny Tiny RSS instance to read articles.
Project-URL: Homepage, https://github.com/reuteras/ttrsscli
Project-URL: Issues, https://github.com/reuteras/ttrsscli/issues
Author-email: Peter Reuterås <peter@reuteras.net>
License: MIT
License-File: LICENSE
Classifier: Development Status :: 7 - Inactive
Classifier: Environment :: Console
Classifier: Operating System :: OS Independent
Classifier: Programming Language :: Python :: 3
Requires-Python: >=3.12
Requires-Dist: beautifulsoup4>=4.13.3
Requires-Dist: cleanurl>=0.1.15
Requires-Dist: h11>=0.16.0
Requires-Dist: httpx>=0.28.1
Requires-Dist: markdownify>=0.14.1
Requires-Dist: readwise-api>=0.3.0
Requires-Dist: requests>=2.32.3
Requires-Dist: textual-serve>=1.1.1
Requires-Dist: textual[syntax]>=5.3.0
Requires-Dist: toml>=0.10.2
Requires-Dist: ttrss-python
